pinot_connect/__init__.py
pinot_connect/_decorators.py
pinot_connect/_query.py
pinot_connect/_result_set.py
pinot_connect/_type_converters.py
pinot_connect/connection.py
pinot_connect/context.py
pinot_connect/cursor.py
pinot_connect/exceptions.py
pinot_connect/options.py
pinot_connect/py.typed
pinot_connect/rows.py
pinot_connect-0.1.1.dist-info/METADATA
pinot_connect-0.1.1.dist-info/WHEEL
pinot_connect-0.1.1.dist-info/RECORD
