Metadata-Version: 2.3
Name: pinot-connect
Version: 0.1.1
Summary: Statically typed DB-API 2.0 driver for Apache Pinot
License: MIT
Author: Zach Schumacher
Author-email: zschu15@gmail.com
Requires-Python: >=3.9,<4.0
Classifier: Development Status :: 4 - Beta
Classifier: Programming Language :: Python :: 3 :: Only
Classifier: Programming Language :: Python :: 3.9
Classifier: Programming Language :: Python :: 3.10
Classifier: Programming Language :: Python :: 3.11
Classifier: Programming Language :: Python :: 3.12
Classifier: Programming Language :: Python :: 3.13
Classifier: Intended Audience :: Developers
Classifier: License :: OSI Approved :: MIT License
Classifier: Operating System :: OS Independent
Classifier: Topic :: Software Development :: Libraries :: Python Modules
Classifier: Topic :: Software Development :: Libraries
Classifier: Topic :: Software Development
Classifier: Topic :: Database
Classifier: Topic :: Database :: Database Engines/Servers
Classifier: Typing :: Typed
Requires-Dist: ciso8601 (>=2.3.2,<3.0.0)
Requires-Dist: httpx (>=0.23.0,<0.29.0)
Requires-Dist: orjson (>=3.10.15,<4.0.0)
Project-URL: Changelog, https://pinot-connect.org/release_notes
Project-URL: Documentation, https://pinot-connect.org/
Project-URL: Homepage, https://github.com/zschumacher/pinot-connect
Project-URL: Issues, https://github.com/zschumacher/pinot-connect/issues
Project-URL: Repository, https://github.com/zschumacher/pinot-connect
